setup.py
huaula/__init__.py
huaula/dunder_main.py
huaula/github.py
huaula/github_import.py
huaula/meu_xml.py
huaula.egg-info/PKG-INFO
huaula.egg-info/SOURCES.txt
huaula.egg-info/dependency_links.txt
huaula.egg-info/not-zip-safe
huaula.egg-info/requires.txt
huaula.egg-info/top_level.txt